Workbook

Sheet Parâmetros
B2: CBS/IBS NA BASE DO ICMS — SIMULADOR DE TRANSIÇÃO
B3: MGK Assessoria e Auditoria | jul/2026 | Preencha apenas as células em AZUL
B5: 1. PREMISSAS COMERCIAIS
B6: Custo do produto (R$) | C6: 1000 | I6: Preço líquido-alvo (vMerc) = Custo x (1 + Margem) - Desconto
B7: Margem sobre o custo (%) | C7: 0.1
B8: Desconto incondicional (R$) | C8: 0
B10: 2. ALÍQUOTAS DE REFERÊNCIA
B11: PIS/COFINS — regime não cumulativo | C11: 0.0925 | I11: LC 10.637/02 e 10.833/03. Base já expurgada do ICMS (STF Tema 69).
B12: CBS — alíquota de referência | C12: 0.088 | I12: Estimativa oficial de referência. ⚠️ ainda não fixada em resolução do Senado.
B13: IBS — alíquota de referência | C13: 0.177 | I13: Estimativa oficial de referência (estadual + municipal). ⚠️
B14: ICMS — alíquota nominal interna | C14: 0.18 | I14: Ajuste conforme UF/produto. ICMS é calculado 'por dentro' (LC 87/96, art. 13, §1º, I).
B15: Redução da CBS em 2027-2028 (p.p.) | C15: 0.001 | I15: LC 214/2025, art. 347: CBS 2027-2028 = alíquota de referência − 0,1 p.p. ✅ confirmado no texto compilado.
B17: 3. CHAVE DE CENÁRIO JURÍDICO
B18: IBS e CBS integram a base de cálculo do ICMS? | C18: Tese do Fisco (INCLUI) | I18: RC SEFAZ/SP 32.303/2025: inclui a partir de 2027; não inclui em 2026. PLP 16/2025 propõe a exclusão expressa.
B19: Chave numérica (automática) | C19: =IF($C$18="Tese do Fisco (INCLUI)",1,0) -> 1
B22: 4. MATRIZ DE ALÍQUOTAS POR ANO DA TRANSIÇÃO
B23: Ano / Cenário | C23: PIS/COFINS | D23: CBS | E23: IBS | F23: % do ICMS vigente | G23: CBS/IBS oneram preço | H23: CBS/IBS na base do ICMS (ano)
B24: Hoje (2025) | C24: =$C$11 -> 0.0925 | D24: 0 | E24: 0 | F24: 1 | G24: 0 | H24: 0
B25: 2026 (teste) | C25: =$C$11 -> 0.0925 | D25: 0.009 | E25: 0.001 | F25: 1 | G25: 0 | H25: 0
B26: 2027 | C26: 0 | D26: =$C$12-$C$15 -> 0.087 | E26: 0.001 | F26: 1 | G26: 1 | H26: 1
B27: 2028 | C27: 0 | D27: =$C$12-$C$15 -> 0.087 | E27: 0.001 | F27: 1 | G27: 1 | H27: 1
B28: 2029 | C28: 0 | D28: =$C$12 -> 0.088 | E28: =$C$13*0.1 -> 0.0177 | F28: 0.9 | G28: 1 | H28: 1
B29: 2030 | C29: 0 | D29: =$C$12 -> 0.088 | E29: =$C$13*0.2 -> 0.0354 | F29: 0.8 | G29: 1 | H29: 1
B30: 2031 | C30: 0 | D30: =$C$12 -> 0.088 | E30: =$C$13*0.3 -> 0.0531 | F30: 0.7 | G30: 1 | H30: 1
B31: 2032 | C31: 0 | D31: =$C$12 -> 0.088 | E31: =$C$13*0.4 -> 0.0708 | F31: 0.6 | G31: 1 | H31: 1
B32: 2033 | C32: 0 | D32: =$C$12 -> 0.088 | E32: =$C$13 -> 0.177 | F32: 0 | G32: 1 | H32: 0
B34: ✅ 2029-2032: a repartição ICMS × IBS (9/10, 8/10, 7/10, 6/10 do ICMS; 10/20/30/40% do IBS de referência) foi CONFIRMADA contra o texto compilado da LC 214/2025 (com LC 227/2026) — é o cronograma legal (ADCT, arts. 128/129; LC 214, arts. 343/344), não simplificação.
B35: Todas as células azuis desta matriz são editáveis — ajuste conforme a alíquota real da UF, do produto e da tese adotada.
B36: Fonte dos valores comerciais (custo 135,30 e margem 10%): fornecidos pelo usuário na planilha original.

Sheet Cenários
B2: LINHA DE CÁLCULO POR ANO DA TRANSIÇÃO
B3: =IF(Parâmetros!$C$19=1,"Cenário ativo: IBS e CBS INTEGRAM a base do ICMS (tese do Fisco)","Cenário ativo: IBS e CBS NÃO integram a base do ICMS (tese do contribuinte)") -> Cenário ativo: IBS e CBS INTEGRAM a base do ICMS (tese do Fisco)
B5: Ano / Cenário | C5: Hoje (2025) | D5: 2026 (teste) | E5: 2027 | F5: 2028 | G5: 2029 | H5: 2030 | I5: 2031 | J5: 2032 | K5: 2033
B6: PREMISSAS
B7: Custo do produto | C7: =Parâmetros!$C$6 -> 1000 | D7: =Parâmetros!$C$6 -> 1000 | E7: =Parâmetros!$C$6 -> 1000 | F7: =Parâmetros!$C$6 -> 1000 | G7: =Parâmetros!$C$6 -> 1000 | H7: =Parâmetros!$C$6 -> 1000 | I7: =Parâmetros!$C$6 -> 1000 | J7: =Parâmetros!$C$6 -> 1000 | K7: =Parâmetros!$C$6 -> 1000
B8: Margem | C8: =Parâmetros!$C$7 -> 0.1 | D8: =Parâmetros!$C$7 -> 0.1 | E8: =Parâmetros!$C$7 -> 0.1 | F8: =Parâmetros!$C$7 -> 0.1 | G8: =Parâmetros!$C$7 -> 0.1 | H8: =Parâmetros!$C$7 -> 0.1 | I8: =Parâmetros!$C$7 -> 0.1 | J8: =Parâmetros!$C$7 -> 0.1 | K8: =Parâmetros!$C$7 -> 0.1
B9: Preço líquido-alvo (vMerc) | C9: =Parâmetros!$C$6*(1+Parâmetros!$C$7) -> 1100 | D9: =Parâmetros!$C$6*(1+Parâmetros!$C$7) -> 1100 | E9: =Parâmetros!$C$6*(1+Parâmetros!$C$7) -> 1100 | F9: =Parâmetros!$C$6*(1+Parâmetros!$C$7) -> 1100 | G9: =Parâmetros!$C$6*(1+Parâmetros!$C$7) -> 1100 | H9: =Parâmetros!$C$6*(1+Parâmetros!$C$7) -> 1100 | I9: =Parâmetros!$C$6*(1+Parâmetros!$C$7) -> 1100 | J9: =Parâmetros!$C$6*(1+Parâmetros!$C$7) -> 1100 | K9: =Parâmetros!$C$6*(1+Parâmetros!$C$7) -> 1100
B10: (-) Desconto incondicional | C10: =Parâmetros!$C$8 -> 0 | D10: =Parâmetros!$C$8 -> 0 | E10: =Parâmetros!$C$8 -> 0 | F10: =Parâmetros!$C$8 -> 0 | G10: =Parâmetros!$C$8 -> 0 | H10: =Parâmetros!$C$8 -> 0 | I10: =Parâmetros!$C$8 -> 0 | J10: =Parâmetros!$C$8 -> 0 | K10: =Parâmetros!$C$8 -> 0
B11: (=) BASE LÍQUIDA — receita que o vendedor quer manter | C11: =C9-C10 -> 1100 | D11: =D9-D10 -> 1100 | E11: =E9-E10 -> 1100 | F11: =F9-F10 -> 1100 | G11: =G9-G10 -> 1100 | H11: =H9-H10 -> 1100 | I11: =I9-I10 -> 1100 | J11: =J9-J10 -> 1100 | K11: =K9-K10 -> 1100
B13: PARÂMETROS APLICADOS AO ANO
B14: Alíquota PIS/COFINS | C14: =INDEX(Parâmetros!$C$24:$C$32,MATCH(C$5,Parâmetros!$B$24:$B$32,0)) -> 0.0925 | D14: =INDEX(Parâmetros!$C$24:$C$32,MATCH(D$5,Parâmetros!$B$24:$B$32,0)) -> 0.0925 | E14: =INDEX(Parâmetros!$C$24:$C$32,MATCH(E$5,Parâmetros!$B$24:$B$32,0)) -> 0 | F14: =INDEX(Parâmetros!$C$24:$C$32,MATCH(F$5,Parâmetros!$B$24:$B$32,0)) -> 0 | G14: =INDEX(Parâmetros!$C$24:$C$32,MATCH(G$5,Parâmetros!$B$24:$B$32,0)) -> 0 | H14: =INDEX(Parâmetros!$C$24:$C$32,MATCH(H$5,Parâmetros!$B$24:$B$32,0)) -> 0 | I14: =INDEX(Parâmetros!$C$24:$C$32,MATCH(I$5,Parâmetros!$B$24:$B$32,0)) -> 0 | J14: =INDEX(Parâmetros!$C$24:$C$32,MATCH(J$5,Parâmetros!$B$24:$B$32,0)) -> 0 | K14: =INDEX(Parâmetros!$C$24:$C$32,MATCH(K$5,Parâmetros!$B$24:$B$32,0)) -> 0
B15: Alíquota CBS | C15: =INDEX(Parâmetros!$D$24:$D$32,MATCH(C$5,Parâmetros!$B$24:$B$32,0)) -> 0 | D15: =INDEX(Parâmetros!$D$24:$D$32,MATCH(D$5,Parâmetros!$B$24:$B$32,0)) -> 0.009 | E15: =INDEX(Parâmetros!$D$24:$D$32,MATCH(E$5,Parâmetros!$B$24:$B$32,0)) -> 0.087 | F15: =INDEX(Parâmetros!$D$24:$D$32,MATCH(F$5,Parâmetros!$B$24:$B$32,0)) -> 0.087 | G15: =INDEX(Parâmetros!$D$24:$D$32,MATCH(G$5,Parâmetros!$B$24:$B$32,0)) -> 0.088 | H15: =INDEX(Parâmetros!$D$24:$D$32,MATCH(H$5,Parâmetros!$B$24:$B$32,0)) -> 0.088 | I15: =INDEX(Parâmetros!$D$24:$D$32,MATCH(I$5,Parâmetros!$B$24:$B$32,0)) -> 0.088 | J15: =INDEX(Parâmetros!$D$24:$D$32,MATCH(J$5,Parâmetros!$B$24:$B$32,0)) -> 0.088 | K15: =INDEX(Parâmetros!$D$24:$D$32,MATCH(K$5,Parâmetros!$B$24:$B$32,0)) -> 0.088
B16: Alíquota IBS | C16: =INDEX(Parâmetros!$E$24:$E$32,MATCH(C$5,Parâmetros!$B$24:$B$32,0)) -> 0 | D16: =INDEX(Parâmetros!$E$24:$E$32,MATCH(D$5,Parâmetros!$B$24:$B$32,0)) -> 0.001 | E16: =INDEX(Parâmetros!$E$24:$E$32,MATCH(E$5,Parâmetros!$B$24:$B$32,0)) -> 0.001 | F16: =INDEX(Parâmetros!$E$24:$E$32,MATCH(F$5,Parâmetros!$B$24:$B$32,0)) -> 0.001 | G16: =INDEX(Parâmetros!$E$24:$E$32,MATCH(G$5,Parâmetros!$B$24:$B$32,0)) -> 0.0177 | H16: =INDEX(Parâmetros!$E$24:$E$32,MATCH(H$5,Parâmetros!$B$24:$B$32,0)) -> 0.0354 | I16: =INDEX(Parâmetros!$E$24:$E$32,MATCH(I$5,Parâmetros!$B$24:$B$32,0)) -> 0.0531 | J16: =INDEX(Parâmetros!$E$24:$E$32,MATCH(J$5,Parâmetros!$B$24:$B$32,0)) -> 0.0708 | K16: =INDEX(Parâmetros!$E$24:$E$32,MATCH(K$5,Parâmetros!$B$24:$B$32,0)) -> 0.177
B17: % do ICMS vigente | C17: =INDEX(Parâmetros!$F$24:$F$32,MATCH(C$5,Parâmetros!$B$24:$B$32,0)) -> 1 | D17: =INDEX(Parâmetros!$F$24:$F$32,MATCH(D$5,Parâmetros!$B$24:$B$32,0)) -> 1 | E17: =INDEX(Parâmetros!$F$24:$F$32,MATCH(E$5,Parâmetros!$B$24:$B$32,0)) -> 1 | F17: =INDEX(Parâmetros!$F$24:$F$32,MATCH(F$5,Parâmetros!$B$24:$B$32,0)) -> 1 | G17: =INDEX(Parâmetros!$F$24:$F$32,MATCH(G$5,Parâmetros!$B$24:$B$32,0)) -> 0.9 | H17: =INDEX(Parâmetros!$F$24:$F$32,MATCH(H$5,Parâmetros!$B$24:$B$32,0)) -> 0.8 | I17: =INDEX(Parâmetros!$F$24:$F$32,MATCH(I$5,Parâmetros!$B$24:$B$32,0)) -> 0.7 | J17: =INDEX(Parâmetros!$F$24:$F$32,MATCH(J$5,Parâmetros!$B$24:$B$32,0)) -> 0.6 | K17: =INDEX(Parâmetros!$F$24:$F$32,MATCH(K$5,Parâmetros!$B$24:$B$32,0)) -> 0
B18: Alíquota ICMS efetiva | C18: =Parâmetros!$C$14*C17 -> 0.18 | D18: =Parâmetros!$C$14*D17 -> 0.18 | E18: =Parâmetros!$C$14*E17 -> 0.18 | F18: =Parâmetros!$C$14*F17 -> 0.18 | G18: =Parâmetros!$C$14*G17 -> 0.162 | H18: =Parâmetros!$C$14*H17 -> 0.144 | I18: =Parâmetros!$C$14*I17 -> 0.126 | J18: =Parâmetros!$C$14*J17 -> 0.108 | K18: =Parâmetros!$C$14*K17 -> 0
B19: CBS/IBS oneram o preço (1/0) | C19: =INDEX(Parâmetros!$G$24:$G$32,MATCH(C$5,Parâmetros!$B$24:$B$32,0)) -> 0 | D19: =INDEX(Parâmetros!$G$24:$G$32,MATCH(D$5,Parâmetros!$B$24:$B$32,0)) -> 0 | E19: =INDEX(Parâmetros!$G$24:$G$32,MATCH(E$5,Parâmetros!$B$24:$B$32,0)) -> 1 | F19: =INDEX(Parâmetros!$G$24:$G$32,MATCH(F$5,Parâmetros!$B$24:$B$32,0)) -> 1 | G19: =INDEX(Parâmetros!$G$24:$G$32,MATCH(G$5,Parâmetros!$B$24:$B$32,0)) -> 1 | H19: =INDEX(Parâmetros!$G$24:$G$32,MATCH(H$5,Parâmetros!$B$24:$B$32,0)) -> 1 | I19: =INDEX(Parâmetros!$G$24:$G$32,MATCH(I$5,Parâmetros!$B$24:$B$32,0)) -> 1 | J19: =INDEX(Parâmetros!$G$24:$G$32,MATCH(J$5,Parâmetros!$B$24:$B$32,0)) -> 1 | K19: =INDEX(Parâmetros!$G$24:$G$32,MATCH(K$5,Parâmetros!$B$24:$B$32,0)) -> 1
B20: CBS/IBS na base do ICMS (1/0) | C20: =INDEX(Parâmetros!$H$24:$H$32,MATCH(C$5,Parâmetros!$B$24:$B$32,0))*Parâmetros!$C$19 -> 0 | D20: =INDEX(Parâmetros!$H$24:$H$32,MATCH(D$5,Parâmetros!$B$24:$B$32,0))*Parâmetros!$C$19 -> 0 | E20: =INDEX(Parâmetros!$H$24:$H$32,MATCH(E$5,Parâmetros!$B$24:$B$32,0))*Parâmetros!$C$19 -> 1 | F20: =INDEX(Parâmetros!$H$24:$H$32,MATCH(F$5,Parâmetros!$B$24:$B$32,0))*Parâmetros!$C$19 -> 1 | G20: =INDEX(Parâmetros!$H$24:$H$32,MATCH(G$5,Parâmetros!$B$24:$B$32,0))*Parâmetros!$C$19 -> 1 | H20: =INDEX(Parâmetros!$H$24:$H$32,MATCH(H$5,Parâmetros!$B$24:$B$32,0))*Parâmetros!$C$19 -> 1 | I20: =INDEX(Parâmetros!$H$24:$H$32,MATCH(I$5,Parâmetros!$B$24:$B$32,0))*Parâmetros!$C$19 -> 1 | J20: =INDEX(Parâmetros!$H$24:$H$32,MATCH(J$5,Parâmetros!$B$24:$B$32,0))*Parâmetros!$C$19 -> 1 | K20: =INDEX(Parâmetros!$H$24:$H$32,MATCH(K$5,Parâmetros!$B$24:$B$32,0))*Parâmetros!$C$19 -> 0
B22: NOVOS TRIBUTOS (cálculo POR FORA — LC 214/2025, art. 12)
B23: Base de cálculo CBS/IBS | C23: =C11 -> 1100 | D23: =D11 -> 1100 | E23: =E11 -> 1100 | F23: =F11 -> 1100 | G23: =G11 -> 1100 | H23: =H11 -> 1100 | I23: =I11 -> 1100 | J23: =J11 -> 1100 | K23: =K11 -> 1100
B24: CBS destacada | C24: =C23*C15 -> 0 | D24: =D23*D15 -> 9.9 | E24: =E23*E15 -> 95.7 | F24: =F23*F15 -> 95.7 | G24: =G23*G15 -> 96.8 | H24: =H23*H15 -> 96.8 | I24: =I23*I15 -> 96.8 | J24: =J23*J15 -> 96.8 | K24: =K23*K15 -> 96.8
B25: IBS destacado | C25: =C23*C16 -> 0 | D25: =D23*D16 -> 1.1 | E25: =E23*E16 -> 1.1 | F25: =F23*F16 -> 1.1 | G25: =G23*G16 -> 19.47 | H25: =H23*H16 -> 38.94 | I25: =I23*I16 -> 58.41 | J25: =J23*J16 -> 77.88 | K25: =K23*K16 -> 194.7
B26: (=) CBS + IBS | C26: =C24+C25 -> 0 | D26: =D24+D25 -> 11 | E26: =E24+E25 -> 96.8 | F26: =F24+F25 -> 96.8 | G26: =G24+G25 -> 116.27 | H26: =H24+H25 -> 135.74 | I26: =I24+I25 -> 155.21 | J26: =J24+J25 -> 174.68 | K26: =K24+K25 -> 291.5
B28: TRIBUTOS DO REGIME ATUAL (cálculo POR DENTRO)
B29: vProd (valor do produto no XML) | C29: =(C11/(1-C14)+C18*C20*C26)/(1-C18) -> 1478.1966 | D29: =(D11/(1-D14)+D18*D20*D26)/(1-D18) -> 1478.1966 | E29: =(E11/(1-E14)+E18*E20*E26)/(1-E18) -> 1362.7122 | F29: =(F11/(1-F14)+F18*F20*F26)/(1-F18) -> 1362.7122 | G29: =(G11/(1-G14)+G18*G20*G26)/(1-G18) -> 1335.1262 | H29: =(H11/(1-H14)+H18*H20*H26)/(1-H18) -> 1307.8815 | I29: =(I11/(1-I14)+I18*I20*I26)/(1-I18) -> 1280.957 | J29: =(J11/(1-J14)+J18*J20*J26)/(1-J18) -> 1254.3335 | K29: =(K11/(1-K14)+K18*K20*K26)/(1-K18) -> 1100
B30: Base de cálculo do ICMS | C30: =C29+C20*C26 -> 1478.1966 | D30: =D29+D20*D26 -> 1478.1966 | E30: =E29+E20*E26 -> 1459.5122 | F30: =F29+F20*F26 -> 1459.5122 | G30: =G29+G20*G26 -> 1451.3962 | H30: =H29+H20*H26 -> 1443.6215 | I30: =I29+I20*I26 -> 1436.167 | J30: =J29+J20*J26 -> 1429.0135 | K30: =K29+K20*K26 -> 1100
B31: ICMS | C31: =C30*C18 -> 266.07539 | D31: =D30*D18 -> 266.07539 | E31: =E30*E18 -> 262.7122 | F31: =F30*F18 -> 262.7122 | G31: =G30*G18 -> 235.12618 | H31: =H30*H18 -> 207.8815 | I31: =I30*I18 -> 180.95705 | J31: =J30*J18 -> 154.33345 | K31: =K30*K18 -> 0
B32: Base de cálculo PIS/COFINS (ex-ICMS) | C32: =C29-C31 -> 1212.1212 | D32: =D29-D31 -> 1212.1212 | E32: =E29-E31 -> 1100 | F32: =F29-F31 -> 1100 | G32: =G29-G31 -> 1100 | H32: =H29-H31 -> 1100 | I32: =I29-I31 -> 1100 | J32: =J29-J31 -> 1100 | K32: =K29-K31 -> 1100
B33: PIS/COFINS | C33: =C32*C14 -> 112.12121 | D33: =D32*D14 -> 112.12121 | E33: =E32*E14 -> 0 | F33: =F32*F14 -> 0 | G33: =G32*G14 -> 0 | H33: =H32*H14 -> 0 | I33: =I32*I14 -> 0 | J33: =J32*J14 -> 0 | K33: =K32*K14 -> 0
B35: RESULTADO DA OPERAÇÃO
B36: vProd (XML) | C36: =C29 -> 1478.1966 | D36: =D29 -> 1478.1966 | E36: =E29 -> 1362.7122 | F36: =F29 -> 1362.7122 | G36: =G29 -> 1335.1262 | H36: =H29 -> 1307.8815 | I36: =I29 -> 1280.957 | J36: =J29 -> 1254.3335 | K36: =K29 -> 1100
B37: TOTAL DA NOTA / preço ao consumidor final | C37: =C29+C26*C19 -> 1478.1966 | D37: =D29+D26*D19 -> 1478.1966 | E37: =E29+E26*E19 -> 1459.5122 | F37: =F29+F26*F19 -> 1459.5122 | G37: =G29+G26*G19 -> 1451.3962 | H37: =H29+H26*H19 -> 1443.6215 | I37: =I29+I26*I19 -> 1436.167 | J37: =J29+J26*J19 -> 1429.0135 | K37: =K29+K26*K19 -> 1391.5
B38: Carga tributária total (R$) | C38: =C31+C33+C26*C19 -> 378.1966 | D38: =D31+D33+D26*D19 -> 378.1966 | E38: =E31+E33+E26*E19 -> 359.5122 | F38: =F31+F33+F26*F19 -> 359.5122 | G38: =G31+G33+G26*G19 -> 351.39618 | H38: =H31+H33+H26*H19 -> 343.6215 | I38: =I31+I33+I26*I19 -> 336.16705 | J38: =J31+J33+J26*J19 -> 329.01345 | K38: =K31+K33+K26*K19 -> 291.5
B39: Carga sobre o total da nota | C39: =IFERROR(C38/C37,0) -> 0.25585 | D39: =IFERROR(D38/D37,0) -> 0.25585 | E39: =IFERROR(E38/E37,0) -> 0.24632353 | F39: =IFERROR(F38/F37,0) -> 0.24632353 | G39: =IFERROR(G38/G37,0) -> 0.24210907 | H39: =IFERROR(H38/H37,0) -> 0.23802742 | I39: =IFERROR(I38/I37,0) -> 0.23407239 | J39: =IFERROR(J38/J37,0) -> 0.23023818 | K39: =IFERROR(K38/K37,0) -> 0.20948617
B40: Carga sobre a base líquida | C40: =IFERROR(C38/C11,0) -> 0.34381509 | D40: =IFERROR(D38/D11,0) -> 0.34381509 | E40: =IFERROR(E38/E11,0) -> 0.32682927 | F40: =IFERROR(F38/F11,0) -> 0.32682927 | G40: =IFERROR(G38/G11,0) -> 0.31945107 | H40: =IFERROR(H38/H11,0) -> 0.31238318 | I40: =IFERROR(I38/I11,0) -> 0.30560641 | J40: =IFERROR(J38/J11,0) -> 0.29910314 | K40: =IFERROR(K38/K11,0) -> 0.265
B41: Δ do preço final vs. hoje (R$) | C41: =C37-$C$37 -> 0 | D41: =D37-$C$37 -> 0 | E41: =E37-$C$37 -> -18.684405 | F41: =F37-$C$37 -> -18.684405 | G41: =G37-$C$37 -> -26.800419 | H41: =H37-$C$37 -> -34.575105 | I41: =I37-$C$37 -> -42.029552 | J41: =J37-$C$37 -> -49.183147 | K41: =K37-$C$37 -> -86.6966
B42: Δ do preço final vs. hoje (%) | C42: =IFERROR(C37/$C$37-1,0) -> 0 | D42: =IFERROR(D37/$C$37-1,0) -> 0 | E42: =IFERROR(E37/$C$37-1,0) -> -0.01264 | F42: =IFERROR(F37/$C$37-1,0) -> -0.01264 | G42: =IFERROR(G37/$C$37-1,0) -> -0.018130483 | H42: =IFERROR(H37/$C$37-1,0) -> -0.023390058 | I42: =IFERROR(I37/$C$37-1,0) -> -0.028432992 | J42: =IFERROR(J37/$C$37-1,0) -> -0.033272399 | K42: =IFERROR(K37/$C$37-1,0) -> -0.05865025
B44: CONTROLES
B45: Receita líquida realizada (deve igualar a base líquida) | C45: =C37-C31-C33-C26*C19 -> 1100 | D45: =D37-D31-D33-D26*D19 -> 1100 | E45: =E37-E31-E33-E26*E19 -> 1100 | F45: =F37-F31-F33-F26*F19 -> 1100 | G45: =G37-G31-G33-G26*G19 -> 1100 | H45: =H37-H31-H33-H26*H19 -> 1100 | I45: =I37-I31-I33-I26*I19 -> 1100 | J45: =J37-J31-J33-J26*J19 -> 1100 | K45: =K37-K31-K33-K26*K19 -> 1100
B46: Diferença (deve ser 0,00) | C46: =C45-C11 -> 0 | D46: =D45-D11 -> 0 | E46: =E45-E11 -> 0 | F46: =F45-F11 -> 0 | G46: =G45-G11 -> 0 | H46: =H45-H11 -> 0 | I46: =I45-I11 -> 0 | J46: =J45-J11 -> 0 | K46: =K45-K11 -> 0

Sheet Sensibilidade
B2: TESE DO FISCO x TESE DO CONTRIBUINTE — IMPACTO ISOLADO
B3: Compara as duas hipóteses simultaneamente, independentemente da chave escolhida na aba Parâmetros.
B5: Ano / Cenário | C5: Hoje (2025) | D5: 2026 (teste) | E5: 2027 | F5: 2028 | G5: 2029 | H5: 2030 | I5: 2031 | J5: 2032 | K5: 2033
B6: A) TESE DO FISCO — IBS/CBS INTEGRAM A BASE DO ICMS
B8: Inclui? (1/0) | C8: =INDEX(Parâmetros!$H$24:$H$32,MATCH(C$5,Parâmetros!$B$24:$B$32,0)) -> 0 | D8: =INDEX(Parâmetros!$H$24:$H$32,MATCH(D$5,Parâmetros!$B$24:$B$32,0)) -> 0 | E8: =INDEX(Parâmetros!$H$24:$H$32,MATCH(E$5,Parâmetros!$B$24:$B$32,0)) -> 1 | F8: =INDEX(Parâmetros!$H$24:$H$32,MATCH(F$5,Parâmetros!$B$24:$B$32,0)) -> 1 | G8: =INDEX(Parâmetros!$H$24:$H$32,MATCH(G$5,Parâmetros!$B$24:$B$32,0)) -> 1 | H8: =INDEX(Parâmetros!$H$24:$H$32,MATCH(H$5,Parâmetros!$B$24:$B$32,0)) -> 1 | I8: =INDEX(Parâmetros!$H$24:$H$32,MATCH(I$5,Parâmetros!$B$24:$B$32,0)) -> 1 | J8: =INDEX(Parâmetros!$H$24:$H$32,MATCH(J$5,Parâmetros!$B$24:$B$32,0)) -> 1 | K8: =INDEX(Parâmetros!$H$24:$H$32,MATCH(K$5,Parâmetros!$B$24:$B$32,0)) -> 0
B9: vProd | C9: =(Cenários!C11/(1-Cenários!C14)+Cenários!C18*C8*Cenários!C26)/(1-Cenários!C18) -> 1478.1966 | D9: =(Cenários!D11/(1-Cenários!D14)+Cenários!D18*D8*Cenários!D26)/(1-Cenários!D18) -> 1478.1966 | E9: =(Cenários!E11/(1-Cenários!E14)+Cenários!E18*E8*Cenários!E26)/(1-Cenários!E18) -> 1362.7122 | F9: =(Cenários!F11/(1-Cenários!F14)+Cenários!F18*F8*Cenários!F26)/(1-Cenários!F18) -> 1362.7122 | G9: =(Cenários!G11/(1-Cenários!G14)+Cenários!G18*G8*Cenários!G26)/(1-Cenários!G18) -> 1335.1262 | H9: =(Cenários!H11/(1-Cenários!H14)+Cenários!H18*H8*Cenários!H26)/(1-Cenários!H18) -> 1307.8815 | I9: =(Cenários!I11/(1-Cenários!I14)+Cenários!I18*I8*Cenários!I26)/(1-Cenários!I18) -> 1280.957 | J9: =(Cenários!J11/(1-Cenários!J14)+Cenários!J18*J8*Cenários!J26)/(1-Cenários!J18) -> 1254.3335 | K9: =(Cenários!K11/(1-Cenários!K14)+Cenários!K18*K8*Cenários!K26)/(1-Cenários!K18) -> 1100
B10: ICMS | C10: =(C9+C8*Cenários!C26)*Cenários!C18 -> 266.07539 | D10: =(D9+D8*Cenários!D26)*Cenários!D18 -> 266.07539 | E10: =(E9+E8*Cenários!E26)*Cenários!E18 -> 262.7122 | F10: =(F9+F8*Cenários!F26)*Cenários!F18 -> 262.7122 | G10: =(G9+G8*Cenários!G26)*Cenários!G18 -> 235.12618 | H10: =(H9+H8*Cenários!H26)*Cenários!H18 -> 207.8815 | I10: =(I9+I8*Cenários!I26)*Cenários!I18 -> 180.95705 | J10: =(J9+J8*Cenários!J26)*Cenários!J18 -> 154.33345 | K10: =(K9+K8*Cenários!K26)*Cenários!K18 -> 0
B11: Total da nota | C11: =C9+Cenários!C26*Cenários!C19 -> 1478.1966 | D11: =D9+Cenários!D26*Cenários!D19 -> 1478.1966 | E11: =E9+Cenários!E26*Cenários!E19 -> 1459.5122 | F11: =F9+Cenários!F26*Cenários!F19 -> 1459.5122 | G11: =G9+Cenários!G26*Cenários!G19 -> 1451.3962 | H11: =H9+Cenários!H26*Cenários!H19 -> 1443.6215 | I11: =I9+Cenários!I26*Cenários!I19 -> 1436.167 | J11: =J9+Cenários!J26*Cenários!J19 -> 1429.0135 | K11: =K9+Cenários!K26*Cenários!K19 -> 1391.5
B13: B) TESE DO CONTRIBUINTE — IBS/CBS FORA DA BASE DO ICMS
B14: vProd | C14: =(Cenários!C11/(1-Cenários!C14))/(1-Cenários!C18) -> 1478.1966 | D14: =(Cenários!D11/(1-Cenários!D14))/(1-Cenários!D18) -> 1478.1966 | E14: =(Cenários!E11/(1-Cenários!E14))/(1-Cenários!E18) -> 1341.4634 | F14: =(Cenários!F11/(1-Cenários!F14))/(1-Cenários!F18) -> 1341.4634 | G14: =(Cenários!G11/(1-Cenários!G14))/(1-Cenários!G18) -> 1312.6492 | H14: =(Cenários!H11/(1-Cenários!H14))/(1-Cenários!H18) -> 1285.0467 | I14: =(Cenários!I11/(1-Cenários!I14))/(1-Cenários!I18) -> 1258.5812 | J14: =(Cenários!J11/(1-Cenários!J14))/(1-Cenários!J18) -> 1233.1839 | K14: =(Cenários!K11/(1-Cenários!K14))/(1-Cenários!K18) -> 1100
B15: ICMS | C15: =C14*Cenários!C18 -> 266.07539 | D15: =D14*Cenários!D18 -> 266.07539 | E15: =E14*Cenários!E18 -> 241.46341 | F15: =F14*Cenários!F18 -> 241.46341 | G15: =G14*Cenários!G18 -> 212.64916 | H15: =H14*Cenários!H18 -> 185.04673 | I15: =I14*Cenários!I18 -> 158.58124 | J15: =J14*Cenários!J18 -> 133.18386 | K15: =K14*Cenários!K18 -> 0
B16: Total da nota | C16: =C14+Cenários!C26*Cenários!C19 -> 1478.1966 | D16: =D14+Cenários!D26*Cenários!D19 -> 1478.1966 | E16: =E14+Cenários!E26*Cenários!E19 -> 1438.2634 | F16: =F14+Cenários!F26*Cenários!F19 -> 1438.2634 | G16: =G14+Cenários!G26*Cenários!G19 -> 1428.9192 | H16: =H14+Cenários!H26*Cenários!H19 -> 1420.7867 | I16: =I14+Cenários!I26*Cenários!I19 -> 1413.7912 | J16: =J14+Cenários!J26*Cenários!J19 -> 1407.8639 | K16: =K14+Cenários!K26*Cenários!K19 -> 1391.5
B18: C) IMPACTO DA CONTROVÉRSIA
B19: ICMS a mais na tese do Fisco (R$) | C19: =C10-C15 -> 0 | D19: =D10-D15 -> 0 | E19: =E10-E15 -> 21.24878 | F19: =F10-F15 -> 21.24878 | G19: =G10-G15 -> 22.477017 | H19: =H10-H15 -> 22.834766 | I19: =I10-I15 -> 22.375812 | J19: =J10-J15 -> 21.149596 | K19: =K10-K15 -> 0
B20: Preço final a mais (R$) | C20: =C11-C16 -> 0 | D20: =D11-D16 -> 0 | E20: =E11-E16 -> 21.24878 | F20: =F11-F16 -> 21.24878 | G20: =G11-G16 -> 22.477017 | H20: =H11-H16 -> 22.834766 | I20: =I11-I16 -> 22.375812 | J20: =J11-J16 -> 21.149596 | K20: =K11-K16 -> 0
B21: Preço final a mais (%) | C21: =IFERROR(C11/C16-1,0) -> 0 | D21: =IFERROR(D11/D16-1,0) -> 0 | E21: =IFERROR(E11/E16-1,0) -> 0.014773914 | F21: =IFERROR(F11/F16-1,0) -> 0.014773914 | G21: =IFERROR(G11/G16-1,0) -> 0.015730083 | H21: =IFERROR(H11/H16-1,0) -> 0.016071917 | I21: =IFERROR(I11/I16-1,0) -> 0.015826815 | J21: =IFERROR(J11/J16-1,0) -> 0.015022473 | K21: =IFERROR(K11/K16-1,0) -> 0
B22: Impacto anual sobre faturamento de R$ 1.000.000 (R$) | C22: =IFERROR((C11/C16-1)*1000000,0) -> 0 | D22: =IFERROR((D11/D16-1)*1000000,0) -> 0 | E22: =IFERROR((E11/E16-1)*1000000,0) -> 14773.914 | F22: =IFERROR((F11/F16-1)*1000000,0) -> 14773.914 | G22: =IFERROR((G11/G16-1)*1000000,0) -> 15730.083 | H22: =IFERROR((H11/H16-1)*1000000,0) -> 16071.917 | I22: =IFERROR((I11/I16-1)*1000000,0) -> 15826.815 | J22: =IFERROR((J11/J16-1)*1000000,0) -> 15022.473 | K22: =IFERROR((K11/K16-1)*1000000,0) -> 0
B24: A linha 22 dimensiona o passivo/contingência: aplique o percentual da linha 21 ao faturamento anual efetivo da operação.

Sheet Notas técnicas
B2: NOTAS TÉCNICAS E FUNDAMENTOS
B3: Classificação de confiança (método MGK): ✅ confirmado em norma publicada | ⚠️ modelo operacional ainda não codificado | ⛔ em aberto
B5: Tema | C5: Grau | D5: Fundamento e observação
B6: IBS/CBS por fora | C6: ✅ | D6: LC 214/2025, art. 12 e CF art. 156-A, §1º, IX: IBS e CBS não integram a própria base nem a base um do outro. Por isso a base dos novos tributos é o preço líquido, sem ICMS/PIS/COFINS.
B7: Tributos antigos fora da base dos novos | C7: ✅ | D7: ADCT (EC 132/2023): ICMS, ISS, IPI, PIS e COFINS não integram a base de cálculo do IBS e da CBS.
B8: IBS/CBS na base do ICMS | C8: ⛔ | D8: CONTROVÉRSIA CENTRAL. A EC 132 não repetiu a vedação recíproca. SEFAZ/SP (RC 32.303/2025) sustenta que IBS e CBS compõem a base do ICMS a partir de 2027, por integrarem o valor total cobrado do adquirente (LC 87/96, art. 13). Em 2026 não integram, pois PIS/COFINS permanecem integrais na base. Entidades (FecomercioSP, ABAT) e boa parte da doutrina defendem o oposto, por analogia ao Tema 69 do STF.
B9: PLP 16/2025 | C9: ⚠️ | D9: Propõe alterar a LC 87/96 e a LC 214/2025 para vedar expressamente a inclusão de IBS/CBS nas bases de ICMS, ISS e IPI. Em tramitação na Câmara. Se aprovado após 2027, abre-se a discussão sobre natureza interpretativa ou modificativa.
B10: Ano-teste 2026 | C10: ✅ | D10: Alíquotas de 0,9% (CBS) e 0,1% (IBS), compensáveis com PIS/COFINS e com recolhimento dispensado ao contribuinte que cumprir as obrigações acessórias (LC 214/2025, arts. 343, 346 e 348). Por isso a matriz marca 'onera preço = 0' em 2026: o destaque é informativo.
B11: Marco de 1º/08/2026 | C11: ✅ | D11: Emissão obrigatória de documento fiscal com destaque de IBS/CBS (art. 619 do Decreto 12.955/2026 e art. 617 da Resolução CGIBS 6/2026). Multa de 1% do valor da operação.
B12: Redução da CBS em 2027-2028 | C12: ⚠️ | D12: A alíquota da CBS é reduzida em 0,1 p.p. em 2027 e 2028 para compensar a alíquota-teste do IBS. Confirmar o dispositivo antes de uso externo; o parâmetro está isolado na célula C15 da aba Parâmetros.
B13: Alíquotas de referência | C13: ⚠️ | D13: CBS 8,8% e IBS 17,7% são estimativas; as alíquotas de referência serão fixadas por resolução do Senado. Trate como premissa, nunca como dado.
B14: Transição 2029-2032 | C14: ⚠️ | D14: ICMS e ISS reduzidos a 9/10, 8/10, 7/10 e 6/10 (ADCT art. 128), com elevação correspondente do IBS. A repartição adotada na matriz é uma simplificação linear — ajuste quando as alíquotas de referência forem publicadas.
B15: PIS/COFINS ex-ICMS | C15: ✅ | D15: A base de PIS/COFINS do cenário 'Hoje' já exclui o ICMS (STF, RE 574.706, Tema 69), o que a planilha original captura corretamente.
B16: Neutralidade para contribuinte | C16: ✅ | D16: Para adquirente com direito a crédito integral, o custo líquido é o mesmo em todos os cenários. A controvérsia da base do ICMS afeta caixa, preço ao consumidor final e adquirentes sem crédito (Simples, imunes, consumidor final).
B18: MGK Assessoria e Auditoria | jul/2026 |
